{
  "compileType": "miniprogram",
  "libVersion": "trial",
  "packOptions": {
    "ignore": [
      {
        "value": "/minitest",
        "type": "folder"
      }
    ],
    "include": []
  },
  "setting": {
    "coverView": true,
    "es6": true,
    "postcss": true,
    "minified": true,
    "enhance": true,
    "showShadowRootInWxmlPanel": true,
    "packNpmRelationList": [],
    "babelSetting": {
      "ignore": [],
      "disablePlugins": [],
      "outputPath": ""
    }
  },
  "condition": {},
  "editorSetting": {
    "tabIndent": "auto",
    "tabSize": 2
  },
  "appid": "wx9c5be0910b68f11d",
  "projectname": "miniprogram-3",
  "testRoot": "minitest/"
}